{
    "title" : "Outliers Continued",
    "description" : "<p>Continue building a program that finds all the outliers in a column. In this program, add a counter variable for outliers. Then have the program output the number of outliers found. If no outliers are found, output a message that tells the user that no outliers were found. You should expect the program to output the following when it is working.</p><p><code>200.0 is an outlier.<br>1 outliers found.</code></p><p>Once you have a functioning program, search the other columns for outliers to test different outcomes by changing the parameter 9 to 8 in two different blocks. For example, column 8 has no outliers and produces the following output.</p><p><code>No outliers found.</code></p>",
    "id" : "practice",
    "tray" : "practice.xml",
    "answer" : ["200.0 is an outlier.", "1 outliers found."],
    "hint" : "<p>Drop in the counter variable with the other variable difinitions. Then add to the counter when an outlier is found. Finally at the end of the program use an if-else block to output the number of outlier found, otherwise output &quot;no outliers found.&quot;</p>",
    "code" : {
        "1": "practice.quorum"
    }
}