{
    "title" : "Output Order",
    "description" : "Practice putting output blocks in order. Move each block so the program displays the correct answer after each question.",
    "id" : "order",
    "tray" : "order.xml",
    "answer" : ["Question: What does 3 x 5 equal?","Answer: 15","Question: What does 8 - 5 equal?","Answer: 3","Question: What does 15 + 9 equal?","Answer: 24"],
    "hint" : "<p>Select one answer block and drag it below its matching question. If you are using the keyboard, use cut and paste to move each answer block</p>",
    "code" : {
        "1": "order.quorum"
    }
}