{
    "title" : "Add a Button",
    "description" : "<p>Build a basic application that contains a next button. Set the text of the button. The button won't do anything yet. Later, you will learn about behaviors and be able to program a button to do something.</p><p>After selecting to run this form app, similar to the chart apps, the stop button should be used to end the program.</p>",
    "id" : "button",
    "tray" : "button.xml",
    "answer" : [],
    "hint" : "<p>First, drag over the add button action block. The block adds the button to the page object and should be placed after the page object is made. Finally, change the text to the word next.</p>",
    "code" : {
        "1": "button.quorum"
    }
}